reverse_words/__init__.py
reverse_words/reverse.py
tests/__init__.py
tests/test_reverse.py
reverse_words_package-0.1.2.dist-info/METADATA
reverse_words_package-0.1.2.dist-info/WHEEL
reverse_words_package-0.1.2.dist-info/top_level.txt
reverse_words_package-0.1.2.dist-info/RECORD
